{"stylized_network":{"xlim":[0,573],"ylim":[0,573],"linkColor":"#ff7500","linkAlpha":0.5,"nodeStrokeColor":"#555555","nodeStrokeWidth":3,"links":[{"source":"semen","target":"knjaz","width":0.65625,"weight":5},{"source":"semen","target":"sasha","width":0.91875,"weight":7},{"source":"semen","target":"grafinja","width":0.65625,"weight":5},{"source":"semen","target":"pronskij","width":0.65625,"weight":5},{"source":"semen","target":"olgin","width":0.65625,"weight":5},{"source":"semen","target":"knjazhna","width":0.39374999999999993,"weight":3},{"source":"semen","target":"baron","width":0.39374999999999993,"weight":3},{"source":"semen","target":"ugarov","width":0.39374999999999993,"weight":3},{"source":"semen","target":"olenka","width":0.13124999999999998,"weight":1},{"source":"semen","target":"fialkin","width":0.26249999999999996,"weight":2},{"source":"knjaz","target":"sasha","width":0.7874999999999999,"weight":6},{"source":"knjaz","target":"pronskij","width":0.91875,"weight":7},{"source":"knjaz","target":"olenka","width":0.26249999999999996,"weight":2},{"source":"knjaz","target":"knjazhna","width":0.5249999999999999,"weight":4},{"source":"knjaz","target":"grafinja","width":0.5249999999999999,"weight":4},{"source":"knjaz","target":"baron","width":0.39374999999999993,"weight":3},{"source":"knjaz","target":"ugarov","width":0.39374999999999993,"weight":3},{"source":"knjaz","target":"olgin","width":0.5249999999999999,"weight":4},{"source":"knjaz","target":"fialkin","width":0.13124999999999998,"weight":1},{"source":"sasha","target":"knjazhna","width":0.39374999999999993,"weight":3},{"source":"sasha","target":"olenka","width":0.26249999999999996,"weight":2},{"source":"sasha","target":"pronskij","width":1.0499999999999998,"weight":8},{"source":"sasha","target":"grafinja","width":2.0999999999999996,"weight":16},{"source":"sasha","target":"ugarov","width":0.5249999999999999,"weight":4},{"source":"sasha","target":"fialkin","width":0.39374999999999993,"weight":3},{"source":"sasha","target":"baron","width":0.65625,"weight":5},{"source":"sasha","target":"olgin","width":0.65625,"weight":5},{"source":"pronskij","target":"olenka","width":0.26249999999999996,"weight":2},{"source":"pronskij","target":"knjazhna","width":0.5249999999999999,"weight":4},{"source":"pronskij","target":"grafinja","width":1.18125,"weight":9},{"source":"pronskij","target":"olgin","width":0.91875,"weight":7},{"source":"pronskij","target":"baron","width":0.26249999999999996,"weight":2},{"source":"pronskij","target":"ugarov","width":0.26249999999999996,"weight":2},{"source":"pronskij","target":"fialkin","width":0.13124999999999998,"weight":1},{"source":"olenka","target":"knjazhna","width":0.5249999999999999,"weight":4},{"source":"olenka","target":"grafinja","width":0.26249999999999996,"weight":2},{"source":"olenka","target":"baron","width":0.26249999999999996,"weight":2},{"source":"olenka","target":"ugarov","width":0.26249999999999996,"weight":2},{"source":"olenka","target":"olgin","width":0.13124999999999998,"weight":1},{"source":"knjazhna","target":"grafinja","width":0.39374999999999993,"weight":3},{"source":"knjazhna","target":"baron","width":0.39374999999999993,"weight":3},{"source":"knjazhna","target":"ugarov","width":0.39374999999999993,"weight":3},{"source":"knjazhna","target":"olgin","width":0.39374999999999993,"weight":3},{"source":"knjazhna","target":"fialkin","width":0.13124999999999998,"weight":1},{"source":"grafinja","target":"ugarov","width":0.7874999999999999,"weight":6},{"source":"grafinja","target":"fialkin","width":0.39374999999999993,"weight":3},{"source":"grafinja","target":"baron","width":0.91875,"weight":7},{"source":"grafinja","target":"olgin","width":0.91875,"weight":7},{"source":"ugarov","target":"fialkin","width":0.26249999999999996,"weight":2},{"source":"ugarov","target":"baron","width":0.7874999999999999,"weight":6},{"source":"ugarov","target":"olgin","width":0.39374999999999993,"weight":3},{"source":"fialkin","target":"baron","width":0.26249999999999996,"weight":2},{"source":"fialkin","target":"olgin","width":0.13124999999999998,"weight":1},{"source":"baron","target":"olgin","width":0.39374999999999993,"weight":3}],"nodes":[{"id":"semen","x":296.29326755640705,"y":289.21291608992095,"x_canvas":335.4663377820352,"y_canvas":300.0645804496046,"radius":15.862310778250642,"color":"#bff4fa"},{"id":"knjaz","x":277.82090862027127,"y":293.72179049120433,"x_canvas":243.10454310135628,"y_canvas":322.6089524560216,"radius":15.862310778250642,"color":"#bff4fa"},{"id":"sasha","x":280.980247532748,"y":277.00137127706904,"x_canvas":258.9012376637402,"y_canvas":239.00685638534515,"radius":19.51012970972573,"color":"#bff4fa"},{"id":"pronskij","x":304.8753355530009,"y":304.9194400831128,"x_canvas":378.3766777650046,"y_canvas":378.5972004155642,"radius":17.41338009840746,"color":"#bff4fa"},{"id":"olenka","x":258.759976415512,"y":285.8558138499914,"x_canvas":147.79988207756014,"y_canvas":283.27906924995705,"radius":10.776318121606494,"color":"#a5f2c2"},{"id":"knjazhna","x":303.919617990588,"y":269.89276911970455,"x_canvas":373.59808995294,"y_canvas":203.46384559852277,"radius":14.14213562373095,"color":"#a5f2c2"},{"id":"grafinja","x":287.56922209279503,"y":312.20111836752795,"x_canvas":291.84611046397526,"y_canvas":415.0055918376397,"radius":20,"color":"#a5f2c2"},{"id":"ugarov","x":268.66166675182166,"y":266.3280349780422,"x_canvas":197.30833375910834,"y_canvas":185.64017489021103,"radius":14.810632623547093,"color":"#bff4fa"},{"id":"fialkin","x":315.01038502543355,"y":285.3826766935019,"x_canvas":429.0519251271676,"y_canvas":280.91338346750945,"radius":10.16001016001524,"color":"#bff4fa"},{"id":"baron","x":268.4729375784494,"y":306.3002915300555,"x_canvas":196.36468789224682,"y_canvas":385.50145765027764,"radius":15.240015240022862,"color":"#bff4fa"},{"id":"olgin","x":289.13868181826643,"y":260.6855627184254,"x_canvas":299.6934090913321,"y_canvas":157.427813592127,"radius":15.862310778250642,"color":"#bff4fa"}]},"config":{"zoom":3,"node_charge":-45,"node_gravity":0.1,"link_distance":15,"link_distance_variation":0,"node_collision":true,"wiggle_nodes":false,"freeze_nodes":false,"node_fill_color":"#1cf2c7","node_stroke_color":"#555555","node_label_color":"#000000","display_node_labels":true,"scale_node_size_by_strength":false,"node_size":4,"node_stroke_width":1,"node_size_variation":0.5,"link_color":"#ff7500","link_width":0.7,"link_alpha":0.5,"link_width_variation":1,"display_singleton_nodes":true,"min_link_weight_percentile":0,"max_link_weight_percentile":1},"Graph":null}