{"stylized_network":{"xlim":[0,573],"ylim":[0,573],"linkColor":"#ff7500","linkAlpha":0.5,"nodeStrokeColor":"#555555","nodeStrokeWidth":3,"links":[{"source":"MarjaAleksandrovna","target":"Misha","width":2.0999999999999996,"weight":1},{"source":"MarjaAleksandrovna","target":"Lakej","width":2.0999999999999996,"weight":1},{"source":"MarjaAleksandrovna","target":"Sobachkin","width":2.0999999999999996,"weight":1},{"source":"Misha","target":"Lakej","width":2.0999999999999996,"weight":1}],"nodes":[{"id":"MarjaAleksandrovna","x":292.6590400270647,"y":283.0013402710587,"x_canvas":317.2952001353233,"y_canvas":269.00670135529367,"radius":20,"color":"#bd6333"},{"id":"Misha","x":273.06502142919993,"y":293.3938898670106,"x_canvas":219.3251071459997,"y_canvas":320.96944933505324,"radius":16.32993161855452,"color":"#5efa7c"},{"id":"Lakej","x":275.0895465449537,"y":272.5050057944097,"x_canvas":229.44773272476846,"y_canvas":216.52502897204863,"radius":16.32993161855452,"color":"#5efa7c"},{"id":"Sobachkin","x":305.1860175215174,"y":297.09662260826184,"x_canvas":379.930087607587,"y_canvas":339.48311304130925,"radius":11.547005383792516,"color":"#5efa7c"}]},"config":{"zoom":3,"node_charge":-45,"node_gravity":0.1,"link_distance":15,"link_distance_variation":0,"node_collision":true,"wiggle_nodes":false,"freeze_nodes":false,"node_fill_color":"#1cf2c7","node_stroke_color":"#555555","node_label_color":"#000000","display_node_labels":true,"scale_node_size_by_strength":false,"node_size":4,"node_stroke_width":1,"node_size_variation":0.5,"link_color":"#ff7500","link_width":0.7,"link_alpha":0.5,"link_width_variation":1,"display_singleton_nodes":true,"min_link_weight_percentile":0,"max_link_weight_percentile":1},"Graph":null}